tarrian/__init__.py
tarrian/checker.py
tarrian/cli.py
tarrian/config.py
tarrian/installer.py
tarrian/utils.py
tarrian-0.1.12.dist-info/licenses/LICENSE
tarrian-0.1.12.dist-info/METADATA
tarrian-0.1.12.dist-info/WHEEL
tarrian-0.1.12.dist-info/entry_points.txt
tarrian-0.1.12.dist-info/top_level.txt
tarrian-0.1.12.dist-info/RECORD
