Metadata-Version: 2.4
Name: tarrian
Version: 0.1.12
Summary: Pengelola instalasi Bahasa Tarri - seperti Composer untuk Python
Home-page: https://bahasatarri.com
Author: Bahasa Tarri
Author-email: Ketut Dana <danayasa2@gmail.com>
License: MIT License
Project-URL: Homepage, https://bahasatarri.com
Project-URL: Repository, https://github.com/tarri-dev/tarrian
Keywords: tarri,interpreter,language,installer,automation
Classifier: Programming Language :: Python :: 3
Classifier: License :: OSI Approved :: MIT License
Classifier: Operating System :: OS Independent
Classifier: Intended Audience :: Developers
Classifier: Topic :: Software Development :: Build Tools
Requires-Python: >=3.8
License-File: LICENSE
Requires-Dist: requests>=2.25.0
Dynamic: license-file
